[
  {
    "id":NumberLong(5476545235148907582),
    "creator":{
      "id":NumberLong(5563815712304689726),
      "username":"anniv_Adel"
    },
    "caption":{
      "text":"Repère le panneau Ville de Lancy, puis laisse-toi guider par le chemin secret qui descend vers la rivière. Là, au pied des grands arbres, un galet attend patiemment d’être découvert."
    },
    "likes_count":NumberInt(0),
    "comments_count":NumberInt(0),
    "media":[
      {
        "source_url":"https://www.magicfoundation.io/media/mockup/org.rockquest.app/birthdays_adele/PXL_20250920_095527625.RAW-01.COVER.jpg",
        "width":NumberInt(3072),
        "height":NumberInt(4080)
      }
    ],
    "location":{
      "coordinates":[
        6.1173785,
        46.1752984
      ]
    },
    "origin_id":NumberLong(4404623788365143473),
    "created_at":ISODate("2025-05-16T04:32:17.826Z")
  },  
  {
    "id":NumberLong(5476245235148907582),
    "creator":{
      "id":NumberLong(5563815712304689726),
      "username":"anniv_Adel"
    },
    "caption":{
      "text":"Trois arbres chuchotent entre eux comme de vieux sages… Dans l’un d’eux, un singe espiègle a caché le galet."
    },
    "likes_count":NumberInt(0),
    "comments_count":NumberInt(0),
    "media":[
      {
        "source_url":"https://www.magicfoundation.io/media/mockup/org.rockquest.app/birthdays_adele/PXL_20250920_100501305.RAW-01.COVER.jpg",
        "width":NumberInt(3072),
        "height":NumberInt(4080)
      }
    ],
    "location":{
      "coordinates":[
        6.1173397,
        46.1751615
      ]
    },
    "origin_id":NumberLong(4404623788365143473),
    "created_at":ISODate("2025-05-16T04:32:17.826Z")
  }, 
  {
    "id":NumberLong(5476545235143907582),
    "creator":{
      "id":NumberLong(5563815712304689726),
      "username":"anniv_Adel"
    },
    "caption":{
      "text":"Dans le tunnel où se croisent les murmures de la route, un galet rêve paisiblement, bercé par un rayon de lumière."
    },
    "likes_count":NumberInt(0),
    "comments_count":NumberInt(0),
    "media":[
      {
        "source_url":"https://www.magicfoundation.io/media/mockup/org.rockquest.app/birthdays_adele/PXL_20250920_101212886.RAW-01.COVER.jpg",
        "width":NumberInt(3072),
        "height":NumberInt(4080)
      }
    ],
    "location":{
      "coordinates":[
        6.1162116,
        46.1752367
      ]
    },
    "origin_id":NumberLong(4404623788365143473),
    "created_at":ISODate("2025-05-16T04:32:17.826Z")
  }, 
  {
    "id":NumberLong(5476545235148907182),
    "creator":{
      "id":NumberLong(5563815712304689726),
      "username":"anniv_Adel"
    },
    "caption":{
      "text":"Le long de la rivière se dresse un tronc étrange, témoin du temps passé. Dans ses replis, un galet timide s’est glissé, caché aux regards pressés."
    },
    "likes_count":NumberInt(0),
    "comments_count":NumberInt(0),
    "media":[
      {
        "source_url":"https://www.magicfoundation.io/media/mockup/org.rockquest.app/birthdays_adele/PXL_20250920_101604909.RAW-01.COVER.jpg",
        "width":NumberInt(3072),
        "height":NumberInt(4080)
      }
    ],
    "location":{
      "coordinates":[
        6.1158099,
        46.1759063
      ]
    },
    "origin_id":NumberLong(4404623788365143473),
    "created_at":ISODate("2025-05-16T04:32:17.826Z")
  }, 
  {
    "id":NumberLong(547654523148907582),
    "creator":{
      "id":NumberLong(5563815712304689726),
      "username":"anniv_Adel"
    },
    "caption":{
      "text":"Au bas des escaliers qui descendent vers la rivière, un ancien gardien veille. Sous l’ombre d’un serpent invisible, le galet attend, baigné du souffle de l’eau."
    },
    "likes_count":NumberInt(0),
    "comments_count":NumberInt(0),
    "media":[
      {
        "source_url":"https://www.magicfoundation.io/media/mockup/org.rockquest.app/birthdays_adele/PXL_20250920_102329798.RAW-01.COVER.jpg",
        "width":NumberInt(3072),
        "height":NumberInt(4080)
      },
      {
        "source_url":"https://www.magicfoundation.io/media/mockup/org.rockquest.app/birthdays_adele/PXL_20250920_102037379.RAW-01.COVER.jpg",
        "width":NumberInt(3072),
        "height":NumberInt(4080)
      }
    ],
    "location":{
      "coordinates":[
        6.1160685,
        46.176047
      ]
    },
    "origin_id":NumberLong(4404623788365143473),
    "created_at":ISODate("2025-05-16T04:32:17.826Z")
  }, 
  {
    "id":NumberLong(54765452148907582),
    "creator":{
      "id":NumberLong(5563815712304689726),
      "username":"anniv_Adel"
    },
    "caption":{
      "text":"Là où la scène s’anime et où les spectateurs s’installent, un galet malin s’est glissé derrière eux. Si tu tends l’oreille, tu l’entendras jouer en secret sa musique."
    },
    "likes_count":NumberInt(0),
    "comments_count":NumberInt(0),
    "media":[
      {
        "source_url":"https://www.magicfoundation.io/media/mockup/org.rockquest.app/birthdays_adele/PXL_20250920_103032239.RAW-01.COVER.jpg",
        "width":NumberInt(4080),
        "height":NumberInt(3072)
      }
    ],
    "location":{
      "coordinates":[
        6.1164068,
        46.1765677
      ]
    },
    "origin_id":NumberLong(4404623788365143473),
    "created_at":ISODate("2025-05-16T04:32:17.826Z")
  }, 
  {
    "id":NumberLong(5476545238907582),
    "creator":{
      "id":NumberLong(5563815712304689726),
      "username":"anniv_Adel"
    },
    "caption":{
      "text":"Dans le parc des enfants, un petit galet timide se dissimule, espérant passer inaperçu au milieu des rires et des jeux."
    },
    "likes_count":NumberInt(0),
    "comments_count":NumberInt(0),
    "media":[
      {
        "source_url":"https://www.magicfoundation.io/media/mockup/org.rockquest.app/birthdays_adele/PXL_20250920_103522956.RAW-01.COVER.jpg",
        "width":NumberInt(3072),
        "height":NumberInt(4080)
      }
    ],
    "location":{
      "coordinates":[
        6.1172571,
        46.1752809
      ]
    },
    "origin_id":NumberLong(4404623788365143473),
    "created_at":ISODate("2025-05-16T04:32:17.826Z")
  }, 
  {
    "id":NumberLong(547654523507582),
    "creator":{
      "id":NumberLong(5563815712304689726),
      "username":"anniv_Adel"
    },
    "caption":{
      "text":"On dirait que ce galet est tombé du ciel… Les buissons, tendres et feuillus, ont amorti sa chute et l’ont gardé caché."
    },
    "likes_count":NumberInt(0),
    "comments_count":NumberInt(0),
    "media":[
      {
        "source_url":"https://www.magicfoundation.io/media/mockup/org.rockquest.app/birthdays_adele/PXL_20250920_103723222.RAW-01.COVER.jpg",
        "width":NumberInt(3072),
        "height":NumberInt(4080)
      }
    ],
    "location":{
      "coordinates":[
        6.1177515,
        46.1755129
      ]
    },
    "origin_id":NumberLong(4404623788365143473),
    "created_at":ISODate("2025-05-16T04:32:17.826Z")
  }, 
  {
    "id":NumberLong(5475148907582),
    "creator":{
      "id":NumberLong(5563815712304689726),
      "username":"anniv_Adel"
    },
    "caption":{
      "text":"Parmi les plus hauts géants du parc, un galet rêveur s’est perché, feuilletant en secret un livre invisible, attendant que tu lèves les yeux pour l’apercevoir."
    },
    "likes_count":NumberInt(0),
    "comments_count":NumberInt(0),
    "media":[
      {
        "source_url":"https://www.magicfoundation.io/media/mockup/org.rockquest.app/birthdays_adele/PXL_20250920_104326647.RAW-01.COVER.jpg",
        "width":NumberInt(3072),
        "height":NumberInt(4080)
      }
    ],
    "location":{
      "coordinates":[
        6.1175322,
        46.1757736
      ]
    },
    "origin_id":NumberLong(4404623788365143473),
    "created_at":ISODate("2025-05-16T04:32:17.826Z")
  }
]